odooup/__init__.py
odooup/_cache.py
odooup/_helpers.py
odooup/_installers.py
odooup/_modulegraph.py
odooup/cli.py
odooup/clone.py
odooup/init.py
odooup/patches.py
odooup/whitelist.py
odooup-0.1.2.dist-info/METADATA
odooup-0.1.2.dist-info/WHEEL
odooup-0.1.2.dist-info/entry_points.txt
odooup-0.1.2.dist-info/top_level.txt
odooup-0.1.2.dist-info/RECORD
