Metadata-Version: 2.1
Name: odooup
Version: 0.1.2
Summary: Odoo Project puppet master
Home-page: http://github.com/xoe-labs/odooup
Author: XOE Labs
Author-email: info@xoe.solutions
License: LGPLv3+
Platform: UNKNOWN
Classifier: Development Status :: 4 - Beta
Classifier: Intended Audience :: Developers
Classifier: License :: OSI Approved :: GNU Lesser General Public License v3 or later (LGPLv3+)
Classifier: Programming Language :: Python :: 2.7
Classifier: Programming Language :: Python :: 3.5
Classifier: Programming Language :: Python :: 3.6
Classifier: Programming Language :: Python :: 3.7
Classifier: Framework :: Odoo
Requires-Dist: click (>=7.0)
Requires-Dist: click-plugins
Requires-Dist: future
Requires-Dist: appdirs
Requires-Dist: networkx
